libname/__init__.py
libname/fasta_code.py
hcv_genotypes-0.0.1.dist-info/METADATA
hcv_genotypes-0.0.1.dist-info/WHEEL
hcv_genotypes-0.0.1.dist-info/top_level.txt
hcv_genotypes-0.0.1.dist-info/RECORD
