Metadata-Version: 2.1
Name: hcv_genotypes
Version: 0.0.1
Summary: hcv genotypes Dataset
Home-page: https://github.com/irfan112/HCV-subgenotypes
Author: Irfan Hussain
Author-email: ir_hussain@hotmail.com
Classifier: Programming Language :: Python :: 3
Classifier: License :: OSI Approved :: MIT License
Classifier: Operating System :: OS Independent
Requires-Python: >=3.6
